tascpy/__init__.py
tascpy/experiment.py
tascpy/py.typed
tascpy/domains/__init__.py
tascpy/domains/converters.py
tascpy/domains/coordinate.py
tascpy/domains/factory.py
tascpy/domains/load_displacement.py
tascpy/operations/__init__.py
tascpy/operations/list_proxy.py
tascpy/operations/proxy.py
tascpy/operations/registry.py
tascpy/operations/stub_generator.py
tascpy/operations/__pycache__/__init__.cpython-312.pyc
tascpy/operations/__pycache__/list_proxy.cpython-312.pyc
tascpy/operations/__pycache__/proxy.cpython-312.pyc
tascpy/operations/__pycache__/registry.cpython-312.pyc
tascpy/operations/__pycache__/stub_generator.cpython-312.pyc
tascpy/operations/coordinate/__init__.py
tascpy/operations/coordinate/basic.py
tascpy/operations/coordinate/distance.py
tascpy/operations/coordinate/interpolation.py
tascpy/operations/coordinate/plot.py
tascpy/operations/coordinate/__pycache__/__init__.cpython-312.pyc
tascpy/operations/coordinate/__pycache__/basic.cpython-312.pyc
tascpy/operations/coordinate/__pycache__/distance.cpython-312.pyc
tascpy/operations/coordinate/__pycache__/interpolation.cpython-312.pyc
tascpy/operations/coordinate/__pycache__/plot.cpython-312.pyc
tascpy/operations/core/__init__.py
tascpy/operations/core/combine.py
tascpy/operations/core/filters.py
tascpy/operations/core/interpolate.py
tascpy/operations/core/math.py
tascpy/operations/core/plot.py
tascpy/operations/core/search.py
tascpy/operations/core/select.py
tascpy/operations/core/split.py
tascpy/operations/core/stats.py
tascpy/operations/core/transform.py
tascpy/operations/core/__pycache__/__init__.cpython-312.pyc
tascpy/operations/core/__pycache__/combine.cpython-312.pyc
tascpy/operations/core/__pycache__/filters.cpython-312.pyc
tascpy/operations/core/__pycache__/interpolate.cpython-312.pyc
tascpy/operations/core/__pycache__/math.cpython-312.pyc
tascpy/operations/core/__pycache__/plot.cpython-312.pyc
tascpy/operations/core/__pycache__/search.cpython-312.pyc
tascpy-0.1.0.dist-info/licenses/LICENSE
tascpy-0.1.0.dist-info/METADATA
tascpy-0.1.0.dist-info/WHEEL
tascpy-0.1.0.dist-info/top_level.txt
tascpy-0.1.0.dist-info/RECORD
